{
    "<page title>": "High Quality Purple Camera Bags,Beauty Digital Camera Bag - Buy Beauty Digital Camera Bag,Camera Bag,Camera Case Product on Alibaba.com",
    "capacity": "1 Camera + 1 Lens + Accessories",
    "color": "Black 40GP=12400PCS",
    "delivery time": "1.Our EIRMAI logo:7 days",
    "fob price": "US $7 - 10 / Piece Get Latest\nPrice",
    "item no": "EMB-SS12 PACKING DIMENTIONS 76*47*61 cm(L*W*H)",
    "material": "Nylon LOADING QTY 20GP=6000PCS",
    "minorder quantity": "300 Piece/Pieces",
    "moq": "1.Our EIRMAI logo:30PCS",
    "net weight": "0.48kg",
    "package": "1.1PC in a PP bag",
    "payment method": "L/C,T/T,Paypal,Escrow,Western Union",
    "payment terms": "L/C,T/T",
    "port": "Ningbo",
    "sample time": "1.Our EIRMAI logo:5 days",
    "size": "Outer Size:W179*D129*H230mm",
    "supply ability": "10000 Piece/Pieces per Month"
}