{
    "<page title>": "Metal Bullet Ir Cmos 1.0mp 720p Ahd Camera Cctv Camera - Buy Ahd Camera,Cmos Camera,Cctv Camera Product on Alibaba.com",
    "advanced image": "Sharpness",
    "blchlc": "Auto",
    "daynight": "Yes, IR cut filter automatically switch",
    "defog": "Yes",
    "dwdr": "Yes",
    "electronic shutter": "Auto/Manual",
    "frame rate": "30fps(60Hz), 25 fps(50Hz)",
    "image sensor": "1/4\" CMOS OV9712 +Nextchip 2431 DSP",
    "ir distance": "15-20M",
    "ir led": "24 units 850nm Infrared LED",
    "lens": "3.6mm fixed lens",
    "minimum illumination": "Color:0. 1Lux@(F1.2,AGC ON),0Lux with IR ON",
    "mirror": "Yes",
    "model": "SS-117A19",
    "motion decetion": "Up to 4 areas",
    "net weight": "400g",
    "power supply": "DC12V\u00b110%",
    "privacy mask": "Up to 4 area",
    "resolution": "1280(V)x720(H)",
    "sens up": "Yes",
    "shutter": "1/50(1/60)sec to 1/100,000sec",
    "signal system": "PAL/NTSC",
    "sn ratio": ">54dB(AGC off)",
    "view angle": "approx.80\u00b0",
    "white balance": "Auto",
    "working working environment": "(-10\u00b0C~+50\u00b0C),RH90% MAX(non-condencing)"
}