{
    "<page title>": "Cheap Mini Digital Camera - Buy Cheap Mini Digital Camera,Cheap Mini Digital Camera,Cheap Mini Digital Camera Product on Alibaba.com",
    "antishake": "YES",
    "aperture": "N/A",
    "build in speaker": "N/A",
    "buildin microphone": "YES",
    "continuous shot": "N/A",
    "default resolution": [
        "HD (1280x720)Pixels @30fps",
        "1.3 Mega Pixels (1280\u00d71024)"
    ],
    "digital  optical zoom": "N/A",
    "dimensions": "2.6*3.8*6cm",
    "driving recorder": "YES",
    "ev compensation": "Auto",
    "external memory": "TF Card up to 32GB",
    "face detection": "N/A",
    "flash mode": "2* Super LED Light",
    "fob price": "US $20 - 30 / Piece Get Latest\nPrice",
    "focus": "120\u00b0 wide-angel lens",
    "hdmi port": "N/A",
    "image file format": "JPEG",
    "image sensor": "1.3 Mega Pixels CMOS Sensor",
    "internal memory": "SDRAM 8\u00d716Mb (No storage function)&SPI 2MB.",
    "lcd display": "Four Digital\u201c8888+ICON\u201d Monochrome LCD Display",
    "mass storage fucntion": "YES",
    "minorder quantity": "1 Piece/Pieces",
    "model nunber": "Sunplus SPCA1628",
    "osd language": "N/A",
    "payment terms": "L/C,D/A,D/P,T/T,Western Union,MoneyGram,Paypal",
    "pc camera": "N/A",
    "pc interface": "USB 2.0",
    "playback": "N/A",
    "port": "SHENZHEN",
    "power life": "more than one 3.5 Hours",
    "power source": "Lithium 1000MA",
    "scenes": "Auto",
    "selftimer": "N/A",
    "sensitivity": "Auto",
    "shutter control": "Electronics",
    "smile shot": "N/A",
    "still image resolution": "3.1Mega Pixels (2048\u00d71536) ,1.3 Mega Pixels (1280\u00d71024)",
    "supply ability": "100000 Piece/Pieces per Month",
    "supported os": "Microsoft Windows 2000,XP,VISTA,Windows 7",
    "video file format": "AVI",
    "video out": "N/A",
    "video resolution": "HD (1280x720)Pixels @30fps;VGA(640*480)Pixels @60fps",
    "video with sound": "YES",
    "view finder": "N/A",
    "waterproof with case": "10meters",
    "white balance": "Auto"
}