{
    "<page title>": "Fashion Waterproof Case For Camera - Buy Genuine Waterproof Case For Camera,Oem Waterproof Case For Camera,High Quality Waterproof Case For Camera Product on Alibaba.com",
    "color": "Black, Navy, Red, Dark Grey, Green, White; As custom's require.",
    "feature": "1.waterproof and shockproof",
    "fob price": "US $0.95 - 2.1 / Piece Get Latest\nPrice",
    "logo": "sublimation print,silk screen print,transfer print all are available",
    "minorder quantity": "500 Piece/Pieces fashion waterproof case for camera",
    "name": "fashion waterproof case for camera",
    "optional fabric": "Neoprene/EVA/Nylon",
    "payment terms": "D/P,T/T,Western Union",
    "port": "Shanghai Port or any main port in China",
    "sample": "7days,mass production:25days",
    "shipment": "By AIR or SEA. Sample by DHL, or UPS, EMS,",
    "style no": "CM3001",
    "supply ability": "20000 Piece/Pieces per Month fashion waterproof case for camera"
}