{
    "<page title>": "Telesin Professional Gopro Silicone Case For Gopro Hero 3 + - Buy Silicone Case For Gopro Hero 3,Gopro Silicone Case For Gopro Hero 3,Telesin Silicone Case For Gopro Hero 3 Product on Alibaba.com",
    "brand": "Telesin",
    "color": "Black",
    "compatible": "gopro hero 3",
    "item name": "Telesin professional gopro protective side frame",
    "item no": "GP-PTC-310",
    "material": "Silicone",
    "package": "1* gopro frame",
    "size": "6.7*5*6CM",
    "warranty": "1 year",
    "weight": "15g"
}