{
    "<page title>": "Panasonic DMC-G10 Interchangeable Lens System Digital Camera Reviews | Buzzillions.com",
    "accessory shoe": "Yes",
    "anti shake mode": "Yes",
    "card slot": [
        "Secure Digital",
        "SDHC",
        "SDXC"
    ],
    "compatible battery": [
        "DMW-BLB13",
        "ProMaster DMW-BLB13"
    ],
    "depth inches": "2.91",
    "digital slr": "Body With Lens",
    "effective megapixel count": "12.1",
    "electronic flash": "Built-in",
    "exposure modes": [
        "Program AE",
        "Manual",
        "Aperture-Priority AE",
        "Shutter-Priority AE"
    ],
    "filterwide angle capability": "52mm",
    "flash": [
        "Slow Synchro",
        "Built-in with Red Eye Reducer",
        "On",
        "Off"
    ],
    "hdmi mini": "Yes",
    "height inches": "3.29",
    "image format": [
        "RAW",
        "JPEG"
    ],
    "lcd display size inches": "3.0",
    "lcd viewer": "3 Inch",
    "lens": "Zoom Lens",
    "lens mount": "Micro Four Thirds",
    "megapixels": "12.1",
    "microphone": "Mono",
    "model": "DMCG10K",
    "movie mode": [
        "Motion JPEG",
        "848x480",
        "640 x 480",
        "320 x 240",
        "1280 x 720"
    ],
    "optical zoom": "3x",
    "removable memory type": [
        "Secure Digital",
        "SDXC",
        "SDHC"
    ],
    "self timer": [
        "2 Seconds",
        "10 Seconds"
    ],
    "sensitivity": "ISO 100-6400",
    "shutter speed": "1/4000-60",
    "speakers": "Built-in",
    "specification": "Description",
    "still image resolution max": "4000 x 3000",
    "still picture capture": "Yes",
    "storage media type": "SD - SDHC - SDXC",
    "usb port": "Mini-B",
    "video movie capture": "1280x720",
    "white balance": [
        "Auto",
        "Color Temperature Setting",
        "White Set",
        "Shade",
        "Cloudy",
        "Flash",
        "Halogen",
        "Daylight"
    ],
    "width inches": "4.88"
}