{
    "<page title>": "Best Digital Cameras For Sightseeing | Olympus FE-230 Digital Camera Reviews - Buzzillions.com",
    "anti shake mode": "Yes",
    "builtin memory": "21MB",
    "camera color": [
        "Black",
        "Silver"
    ],
    "color": "Black",
    "compatible with macintosh": "Yes",
    "compatible with windows pc": "Yes",
    "digital zoom": "4x",
    "display screen": "2.5\" Color LCD 154 Kilopixels",
    "electronic flash": "Built-in",
    "focus mode": [
        "Auto Focus iESP Face Detection",
        "Auto Focus - iESP, Face Detection"
    ],
    "internal memory": "20.5MB",
    "lcd viewer": "2.5 Inch",
    "lens": "Zoom Lens",
    "megapixels": "8.0",
    "memory type": "XD Card Picture",
    "optical zoom": "5x",
    "pictbridge": "Compatible",
    "pixel count": "8 Megapixel",
    "resolution": "8.0 Megapixels",
    "select camera style": "Point & Shoot with Zoom Lens",
    "select media": "Internal Memory,xD Picture Cards",
    "self timer": "Yes",
    "sku": [
        "73407 Black",
        "58134"
    ],
    "skuprice": [
        "124.9900",
        "179.9900"
    ],
    "sound": "Yes",
    "specification": "Description",
    "standard warranty": "1 Year(s)",
    "still picture capture": "Yes",
    "storage media type": "XD PictureCard",
    "style": [
        "OLYFE230",
        "OLYFE310"
    ],
    "taxable": "Y",
    "trackinglinkbaseurl": "http://www.meijer.com",
    "trackinglinkuri": "/catalog/",
    "video movie capture": "VGA - Up to 640x480"
}