{
    "<page title>": "Fujifilm FinePix F900EXR Digital Camera, Black Reviews | Buzzillions.com",
    "age filter code": "060,070,080",
    "age range maximum": "300",
    "age range minimum": "96",
    "anti shake mode": "Yes",
    "bpp bucket": "3781960",
    "bpp eligible": "Yes",
    "builtin memory": "21MB",
    "camera type": "Point & Shoot with Zoom Lens",
    "channel availability": "Online Only",
    "compatible with macintosh": "Yes",
    "compatible with windows pc": "Yes",
    "corp national status": "A",
    "date 1st available online": "18-FEB-13",
    "digital zoom": "2x",
    "electronic flash": "Built-in",
    "freight class": "TRU_SHPG",
    "fulfillment option": "SP",
    "hazmat warning": "N",
    "lcd viewer": "3 Inch",
    "lens": "Zoom Lens",
    "manufacturer part number": "FPF900EXRBLK",
    "manufacturers warranty  hardware": "1 Year",
    "megapixels": "16 Megapixels",
    "notify me when available": "Yes",
    "optical zoom": "20x",
    "pictbridge": "Compatible",
    "promo financing available": "Yes",
    "registerable": "Yes",
    "sensor": "CMOS",
    "sound": "Yes",
    "specification": "Description",
    "still picture capture": "Yes",
    "storage media type": "SD - SDHC - SDXC",
    "tru age range": "8 years and up",
    "tru skn": "542388",
    "video movie capture": "1920x1080",
    "wifi mode": "Included"
}