{
    "<page title>": "Kodak EasyShare M340 10.2MP Digital Camera Reviews | Buzzillions.com",
    "bpp bucket": "3781960",
    "camera color": "Silver",
    "channel availability": "Online Only",
    "color": "Silver",
    "corp national status": "A",
    "date 1st available online": "15-JUL-09",
    "digital zoom": "5x",
    "display screen": "2.7\"",
    "electronic flash": "Built-in",
    "focus mode": "Auto-focus",
    "freight class": "TRU_SHPG",
    "fulfillment option": "SP",
    "hazmat warning": "N",
    "internal memory": "16MB",
    "lcd viewer": "3 Inch",
    "lens": "Zoom Lens",
    "manufacturer part number": "M340RED",
    "megapixels": "10.2",
    "memory type": "Secure Digital (SD) Card",
    "optical zoom": [
        "5x",
        "3x"
    ],
    "pictbridge": "Compatible",
    "registerable": "Yes",
    "resolution": "10.2Megapixel",
    "sku": "168716 SILVER",
    "skuprice": "124.9900",
    "sound": "Yes",
    "specification": "Description",
    "standard warranty": "1 Year",
    "still picture capture": "Yes",
    "storage media type": [
        "Secure Digital (SD)",
        "SD Secure Digital or MMC Multimedia Card"
    ],
    "style": "KodakM340",
    "taxable": "Y",
    "text attribute 1": "Kodaks exclusive Smart Capture feature automatically identifies the scene and adjusts camera settings for a great picture in just about any environmen",
    "text attribute 2": "Upload and share your pictures and videos to YouTube and Kodak Gallery via the Share button and Kodak EasyShare software.",
    "text attribute 3": "Dont miss a shot with the security of in-camera charging and the power of the included Kodak Li-Ion rechargeable digital camera battery.",
    "text attribute 4": "Advanced video features include audio capture, playback, on-camera editing, and prints from video (1, 4, 9 and 16-up). Take stunning HD pictures and v",
    "text attribute 5": "Combine up to three shots into one large picture with on-camera panorama stitch mode. Has 16MB internal flash memory and supports Secure Digital High",
    "trackinglinkbaseurl": [
        "http://www.beachaudio.com",
        "http://www.meijer.com"
    ],
    "trackinglinkuri": [
        "/catalog/",
        "/product_info.php?products_id=261731&src=pwr"
    ],
    "tru skn": "492089",
    "upceanisbn": "041778773208",
    "video movie capture": "VGA - Up to 640x480"
}