{
    "<page title>": "Ricoh GR Price in India with Offers, Reviews & Full Specifications | PriceDekho.com",
    "bangalore": "Hyderabad Chennai Mumbai Delhi Pune",
    "color": "Black",
    "digital zoom": "NA",
    "dust reduction": "NA",
    "external memory": "Yes",
    "face detection": "Yes; Up to 10 Faces",
    "focal length": "18.3 mm (28 mm)",
    "gps": "NA",
    "hdmi": "NA",
    "metering": "NA",
    "optical sensor resolution in megapixel": "16 MP",
    "optical zoom": "1x",
    "other resolution": "NA",
    "other zoom type": "NA",
    "screen size": "3 Inches",
    "usb": "Yes",
    "video display resolution": "NA",
    "white balancing": "Auto, Bracketing, Cloudy, Cool White, Daylight, Details, Incandescent-1, Incandescent-2, Manual, Multi-P Auto, Neutral White, Outdoors, Shade, Warm White"
}