{
    "<page title>": "Samsung Galaxy GC100 Point & Shoot Price in India with Offers, Reviews & Full Specifications | PriceDekho.com",
    "additional features": "Action Freeze, Action Freeze and Light Trace), Audio Capture, Auto Cloud Back-up of Images, Battery Pack, Beautiful Sunset, Blue Sky, Built-in GPS, Creative Controls, Digital Video Capture, Expert Mode, GLONASS), GPS Notes (A GPS, Light Trace, Magic of Wi-Fi Direct, Minimal Organic Design, Mono Speakers, Movie Wizard, Natural Green, Photo Wizard (65 Powerful Editing Features on Board), Recording Resolution (720 x 480 at 120 fps), Remote Viewfinder Control (Including Zoom In / Out, Rich Tone, Scene Mode (Macro, Seamless Connectivity (3G and Wi-Fi), Shoot and Share Photos on-the Spot, Shutter Release), Silhouette, Slow Motion Video, Smart Content Manager (Creating Folders, Smart Pro Mode and Casual Mode (HDR, Tagging Faces and Making Suggestions to Smart Delete Pictures), Tripod Capability, Ultra Sharp 308 Pixels per inch and Full Spectrum of Glorious Colors, Vivid Fireworks), Voice Control, Waterfall Trace, White Magic Technology",
    "bangalore": "Hyderabad Chennai Mumbai Delhi Pune",
    "bluetooth": "No",
    "brand": "Samsung",
    "color": "NA",
    "dimensions": "129 x 71 x 19 mm",
    "display type": "HD Super Clear Touchscreen Display",
    "dust reduction": "NA",
    "ebay": "Snapdeal Flipkart",
    "external memory": "NA",
    "face detection": "Yes; Face Detection AE",
    "focal length": "23 - 481 mm (35 mm Equivalent)",
    "gps": "NA",
    "hdmi": "Yes",
    "iso rating": "Auto / 100 / 200 / 400 / 800 / 1600 / 3200",
    "lens type": "Samsung Lens",
    "memory card type": "microSD, microSDHC, microSDXC",
    "metering": "NA",
    "microphone": "Stereo Microphone",
    "optical sensor resolution in megapixel": "16.3 MP",
    "optical zoom": "20.9x",
    "other resolution": "NA",
    "other zoom type": "NA",
    "picture angle": "23 mm Wide Angle",
    "screen size": "4.7 Inches",
    "sensor size": "1/2.3 Inches",
    "sensor type": "BSI CMOS Sensor",
    "status": "Available",
    "upgradeable memory": "Yes",
    "usb": "Yes",
    "video display resolution": "1920 x 1080 pixels (Full HD) @ 30 fps",
    "weight": "305 gms"
}