{
    "<page title>": "Fujifilm FinePix F550EXR - Price comparison & reviews - Digital Cameras - Australia",
    "camera type": "Compact",
    "digital camera warehouse": "NSW, VIC, QLD",
    "digital camera warehouse nsw vic qld": "Fujifilm FinePix F550EXR Digital Camera - 16 Megapixel +BONUS 4GB SDHC memory card!\nContinuing the excellence of Fujifilm's F-series compact digital cameras, the Fuji FinePix F550 EXR combines a high quality 15x optical zoom Fujinon lens with 24mm wide-angle and an all-new 16 Megapixel BSI EXR CMOS sensor delivering exceptional low-light performance. Also sporting a 3.0 inch high r...\nGenuine Australian Warranties Fast Delivery!\n$305.00\nSee Site\nSee offer",
    "dimensions": "104 x 63 x 33 mm",
    "lcd size": "3 \"",
    "optical image stabilization": "Yes",
    "product name": "\u00bb Show All Product Descriptions",
    "sensor resolution": "16 Mpx",
    "sensor resolution mpx": "16",
    "shop": "Product Name\u00bb Show All Product Descriptions Price Availability",
    "the bad": "Pop up flash, Slow starting up, Weak on low lighted places",
    "the good": "With GPS, Reliable features, Great Images, All-around, Affordable",
    "vic": "Fujifilm FinePix F550EXR BLACK 16MP EXR ,15x Optical Zoom, ISO 12800, 3\" LCD, G (5-75515)\nCameras::Still Camera\nSupplies, Service & Support - Aust Warranty\n$525.29\nAvailable\nSee offer",
    "video resolution": "1920x1080 px",
    "weight": "215 g",
    "zoom": "15 x"
}