{
    "<page title>": "Canon PowerShot SX700 HS Digital Camera - Red (9339B014AA) - Wex Photographic",
    "an": "image is incorrect",
    "battery model": "NB-6LH",
    "cant find a": "related accessory",
    "card format": "SD, SDHC and SDXC",
    "colour": "Red",
    "connectivity": "Hi-Speed USB, HDMI Mini Connector, Wi-Fi",
    "file formats": "JPEG, MP4",
    "flash type": "Built-in",
    "focal length tele": "750",
    "focal length wide": "25",
    "iso max": "3200",
    "iso min": "100",
    "max aperture tele": "6.9",
    "max aperture wide": "3.2",
    "megapixels": "16.1",
    "minimum focus distance": "1cm",
    "movie mode": "1080p",
    "needs additional": "specifications",
    "optical zoom x": "30.0",
    "please add": "more image angles",
    "requires": "compatibility information",
    "resolution": "4608 x 3456",
    "screen resolution pixels": "922000",
    "screen size inches": "3.0",
    "sensor size": "1/2.3 inch",
    "sensor type": "CMOS",
    "shutter speed max": "1/3200 sec",
    "shutter speed min": "15 sec",
    "size": "112.7 x 65.8 x 34.8 mm",
    "the description needs": "further detail",
    "the information is": "incorrect",
    "viewfinder type": "PureColor II G (TFT)",
    "weight g": "269"
}