{
    "<page title>": "Brand New Canon PowerShot SX280 HS Digital Camera 20x Zoom w WiFi GPS Black | eBay",
    "brand": "Canon",
    "condition": "New: A brand-new, unused, unopened, undamaged item in its original packaging (where packaging is\napplicable). Packaging should be the same as what is found in a retail store, unless the item is handmade or was packaged by the manufacturer in non-retail packaging, such as an unprinted box or plastic bag. See the seller's listing for full details.\nSee all condition definitions- opens in a new window or tab\n... Read moreabout the condition",
    "country of manufacture": "Japan",
    "manufacturer warranty": "Yes",
    "megapixels": "12.1 MP",
    "model": "SX280 HS",
    "mpn": "8224B001",
    "optical zoom": "20x",
    "screen size": "3\"",
    "type": "Point & Shoot",
    "upc": "013803220438"
}