{
    "<page title>": "Nikon D7000 16 2 Megapixel DX Digital SLR Body Great Camera 23228 018208254682 | eBay",
    "brand": "Nikon",
    "condition": "Used: An item that has been used previously. The item may have some signs of cosmetic wear, but is fully\noperational and functions as intended. This item may be a floor model or store return that has been used. See the seller\u00e2\u0080\u0099s listing for full details and description of any imperfections.\nSee all condition definitions- opens in a new window or tab\n... Read moreabout the condition",
    "megapixels": "16.2 MP",
    "model": "D7000",
    "mpn": "25468",
    "resolution megapixels": "16.2",
    "screen size": "3\"",
    "type": "Digital SLR",
    "upc": "018208254682"
}