{
    "<page title>": "Sony A5000 20 1 MP Wi Fi Digital Camera Silver w 16 50mm Lens Excellent Cond | eBay",
    "brand": "Sony",
    "bundled items": "Case or Bag,Flash,Lens,Lens Filter,Memory Card",
    "condition": "Used: An item that has been used previously. The item may have some signs of cosmetic wear, but is fully\noperational and functions as intended. This item may be a floor model or store return that has been used. See the seller\u00e2\u0080\u0099s listing for full details and description of any imperfections.\nSee all condition definitions- opens in a new window or tab\n... Read moreabout the condition",
    "manufacturer warranty": "No",
    "megapixels": "16.1 MP",
    "model": "5TL",
    "mpn": "NEX5TLS",
    "optical zoom": "3x",
    "screen size": "3\"",
    "type": "Mirrorless Interchangeable Lens"
}