{
    "<page title>": "18MP Underwater Digital Camera Waterproof Dual Screen LOMO and Sketch Effects | eBay",
    "brand": "Fotopix",
    "bundled items": "USB Cable, ArcSoft Media Impression Software, Case or Bag, Memory Card, Strap (Neck or Wrist)",
    "camera technology": "Digital",
    "condition": "New: A brand-new, unused, unopened, undamaged item in its original packaging (where packaging is\napplicable). Packaging should be the same as what is found in a retail store, unless the item is handmade or was packaged by the manufacturer in non-retail packaging, such as an unprinted box or plastic bag. See the seller's listing for full details.\nSee all condition definitions- opens in a new window or tab\n... Read moreabout the condition",
    "focus type": "Auto",
    "manufacturer warranty": "No",
    "megapixels": "10.0 MP standard; 18.0 MP max",
    "model": "DW-6P",
    "optical zoom": "None",
    "screen size": "2.7\" + 1.8\"",
    "type": "Underwater"
}