{
    "<page title>": "Olympus SP-800UZ 14MP Digital Camera on sale for $197.98",
    "camera type": "Point-and-Shoot",
    "deal first added on": "18-June-2010",
    "ean13": "0050332173583",
    "ean14": "00050332173583",
    "last updated": "09-October-2014",
    "lcd screen size": "3 inches",
    "manufacturer": "Olympus",
    "megapixels": "14 MP",
    "optical zoom": "30 x",
    "product name": "Olympus SP-800UZ 14MP Digital Camera with 30x Wide Angle Dual IS Zoom",
    "product number mpn": "SP-800UZ",
    "redeye reduction": "Yes",
    "retail price": "$399.99",
    "upc": "050332173583"
}