{
    "<page title>": "16GB Bundle For Canon PowerShot SX130 IS on sale for $30.90",
    "deal first added on": "26-September-2010",
    "ean13": "0628586165441",
    "last updated": "09-October-2014",
    "manufacturer": "ButterflyPhoto",
    "product name": "16GB Bundle For Canon PowerShot SX130 IS Digital Camera Includes 16GB High Speed SD Memory card + USB 2.0 High Speed Card Reader + Deluxe Carrying Case + Mini Tripod + Clear LCD Screen Protectors + More",
    "retail price": "$89.95",
    "upc": "628586165441"
}