{
    "<page title>": "Nikon Coolpix L120 14.1MP Digital Camera on sale for $159.95",
    "camera type": "Point-and-Shoot",
    "deal first added on": "9-April-2011",
    "ean13": "0018208262533",
    "last updated": "09-October-2014",
    "lcd screen size": "3 inches",
    "manufacturer": "Nikon",
    "megapixels": "14.1 MP",
    "optical zoom": "21 x",
    "product name": "Nikon Coolpix L120 14.1MP Digital Camera with 21x Optical Zoom (Black)",
    "product number mpn": "L120 Black",
    "retail price": "$279.00",
    "upc": "018208262533"
}