{
    "<page title>": "Canon PowerShot SD750 7.1MP Digital Elph on sale for $494.37",
    "deal first added on": "6-April-2008",
    "dimensions": "3.6 x 2.2 x 0.8 in.",
    "ean13": "0013803076615",
    "ean14": "00013803076615",
    "last updated": "09-October-2014",
    "manufacturer": "Canon",
    "megapixel range": "7.0 - 7.9 Megapixels",
    "product name": "Canon PowerShot SD750 7.1MP Digital Elph Camera with 3x Optical Zoom (Black)",
    "product number mpn": "SD750 Digital E",
    "retail price": "$199.99",
    "upc": [
        "013803076615",
        "999999431592"
    ],
    "weight": "2 lbs."
}