{
    "<page title>": "Konica Minolta Dimage E500 5MP Digital on sale for $155.00",
    "deal first added on": "8-June-2005",
    "dimensions": "1.1 x 3.6 x 2.4 in.",
    "ean13": "0043325997150",
    "ean14": "00043325997150",
    "last updated": "09-October-2014",
    "manufacturer": "Konica Minolta",
    "product name": "Konica Minolta Dimage E500 5MP Digital Camera 3x Optical Zoom",
    "product number mpn": "2816-301",
    "retail price": "$229.99",
    "upc": "043325997150",
    "weight": "1 lbs."
}