{
    "<page title>": "Samsung Galaxy Camera on sale for $379.00",
    "camera type": "Point-and-Shoot",
    "deal first added on": "6-December-2013",
    "ean13": "0887276847795",
    "last updated": "09-October-2014",
    "manufacturer": "Samsung",
    "product name": "Samsung Galaxy Camera with Android Jelly Bean v4.2 OS, 16.3MP CMOS with 21x Optical Zoom and 4.8\" Touch Screen LCD (WiFi - White)",
    "product number mpn": "EK-GC110ZWAXAR",
    "retail price": "$449.99",
    "upc": "887276847795"
}