{
    "<page title>": "Buy Pentax K50 Digital SLR Camera 16MP, Black (Body Only) Cameras - Digital - SLR 10883 today at PC Connection",
    "camera type": "SLR camera",
    "color": "Black",
    "display size": "3 in",
    "flash type": "Pop-up flash",
    "megapixels": "16.3 megapixel(s)",
    "optical sensor size": "15.7 x 23.7mm",
    "optical sensor type": "CMOS",
    "optical viewfinder type": "Eye-Level Penta Prism",
    "returns policy": "This product is subject to our return policy. Please see our complete return policy for details.",
    "shooting modes": [
        "Backlight silhouette",
        "Sunset",
        "Food",
        "Night Portrait",
        "Stage",
        "Landscape",
        "Surf & Snow",
        "Children",
        "Night scene",
        "Pet",
        "Macro",
        "Museum",
        "Candle",
        "Forest",
        "Night snapshot",
        "Portrait",
        "Blue sky",
        "Moving object",
        "Night scene HDR"
    ],
    "warranty  labor": "Call for Warranty",
    "warranty  parts": "Call for Warranty"
}