{
    "<page title>": "Buy Sony DSC-TX30 Camera Cameras - Digital - Point & Shoot DSCTX30/P today at PC Connection",
    "camera type": "Compact",
    "color": "Pink",
    "display size": "3.3 in",
    "flash type": "Built-in flash",
    "megapixels": "18.2 megapixel(s)",
    "optical sensor size": "1/2.3\"",
    "optical sensor type": "Exmor R CMOS",
    "returns policy": "Due to manufacturer restrictions, all sales on this item are final.",
    "shooting modes": [
        "Soft skin",
        "Night scene",
        "Night Portrait",
        "Gourmet",
        "Snow",
        "Softsnap",
        "Fireworks Show",
        "Pet",
        "Handheld twilight",
        "Backlight correction HDR",
        "Anti-motion blur",
        "Landscape",
        "High Sensitivity",
        "Magnifying glass",
        "Beach"
    ],
    "warranty  labor": "90 Days",
    "warranty  parts": "1 Year",
    "weight": "4.400 oz"
}