{
    "<page title>": "Canon Digital IXUS 1000 HS digital camera prices, Shopping comparison for Canon IXUS 1000 HS, Buy online in India - ShopMania",
    "af illuminator": "Yes",
    "aperture": "F/3.4-5.6",
    "battery": "Li-Ion",
    "body type": "Compact",
    "brand": "Canon",
    "category": [
        "Digital Cameras",
        "Digital Cameras"
    ],
    "connector type": "Composite / USB / mini HDMI",
    "continuous shooting speed": "6",
    "depth": "22 mm",
    "digital video format": "AVI / MOV / MPEG / H.264",
    "digital zoom": "4x",
    "display form factor": "Fixed",
    "ean": "8714574553252, 8714574553313, 0876544695763, 0876544695770, 0876544695749, 0876544695756, 0876544695794, 8714574553245, 8714574553177, 8714574553153, 8714574553184, 8714574571195",
    "exposure compensation": "-/+ 2 EV range, in 1/3 EV steps",
    "exposure modes": "Aperture Priority / Auto / Custom / Intelligent Auto / Manual / Program / Scene / Shutter Priority",
    "flash modes": "Auto / Manual / Off / On / Red Eye Reduction / Slow Speed Sync",
    "flash range": "3.50 m",
    "flash type": "Built-in",
    "focal length": "6.3 - 63 mm",
    "focal length equivalent to 35mm": "36 - 360 mm",
    "height": "59 mm",
    "image format": "DCF / DPOF / JPEG",
    "image processor": "Digic 4",
    "image resolutions": "640x480 / 1600x1200 / 1824x1368 / 1920x1080 / 2272x1704 / 2816x2112 / 3648x2048 / 3648x2736 / 4000x3000",
    "image stabilizer": "Optical",
    "included accessories": "AV cable / Carrying strap / Charger / USB cable",
    "light sensitivity iso": "Auto / 100 / 200 / 400 / 800 / 1000 / 1600 / 3200 / 6400",
    "manual focus": "Yes",
    "max shutter speed": "1/4000",
    "memory type": "MultiMediaCard / MultiMediaCard Plus / SD / SDHC / SDXC",
    "metering modes": "Center-weighted / Multi / Spot",
    "microphone": "Yes",
    "min shutter speed": "15s (more than 51%)",
    "optical zoom": "10x (more than 83%)",
    "orientation sensor": "Yes",
    "product name": [
        "Canon Digital IXUS 1000 HS",
        "Canon Digital IXUS 1000 HS"
    ],
    "product rating": [
        "4 out of 5",
        "4 out of 5"
    ],
    "recording functions": "Blink Detection\n/ Face Detection\n/ Panorama\n/ Smile Detection",
    "red eye reduction": "Yes",
    "resolution": "10.1 MP",
    "screen resolution": "230000",
    "screen size": "3\" (more than 62%)",
    "screen type": "LCD",
    "self timer delay": "2s / 10s",
    "sensor size": "1/2.3",
    "sensor type": "CMOS",
    "special effects": "Black & White / Color Accent / Color Swap / Contrast / Custom Effect / Darker Skin Tone / Fisheye / Foliage\n/ Lighter Skin Tone / Neutral / Positive Film / Sepia / Vivid",
    "upc": "876544695763, 876544695770, 876544695749, 876544695756, 876544695794",
    "user reviews": [
        "Write a review",
        "Write a review"
    ],
    "video resolution": "320x240 / 640x480 / 1280x720 / 1920x1080",
    "viewfinder coverage": "100%",
    "weight": "190 g",
    "white balance": "Automatic / Custom / Presets",
    "white balance presets": "Cloudy / Daylight / Sunny / Fine / Flash / Fluorescent / Incandescent / Overcast / Tungsten",
    "width": "101 mm"
}