{
    "<page title>": "Canon IXUS 125 HS digital camera prices, Shopping comparison for Canon IXUS 125 HS, Buy online in India - ShopMania",
    "af illuminator": "Yes",
    "aperture": "F/2.7-5.9",
    "battery": "Li-Ion",
    "body type": "Compact",
    "brand": "Canon",
    "category": "Digital Cameras",
    "connector type": "Composite / HDMI / USB / mini HDMI / mini USB",
    "continuous shooting speed": "2",
    "depth": "20 mm",
    "digital video format": "MOV / H.264",
    "digital zoom": "10x",
    "ean": "8714574579139, 8714574579290, 8714574579252, 8714574579214, 8714574579177, 8714574579146, 8714574579221, 8714574579269, 8714574579184",
    "exposure compensation": "-/+ 2 EV range, in 1/3 EV steps",
    "exposure modes": "Auto / Custom / Scene",
    "flash modes": "Auto / Manual / Off / On / Red Eye Reduction / Slow Speed Sync",
    "flash range": "3.50 m",
    "flash type": "Built-in",
    "focal length": "4.3 - 21.5 mm",
    "focal length equivalent to 35mm": "24 - 120 mm",
    "gps": "Yes",
    "height": "57 mm",
    "image format": "DCF / DPOF / JPEG",
    "image processor": "Digic 5",
    "image resolutions": "480x480 / 640x360 / 640x424 / 640x480 / 1200x1200 / 1600x1064 / 1600x1200 / 1920x1080 / 2448x2448 / 3264x1832 / 3264x2176 / 3264x2448 / 3456x3456 / 4608x2592 / 4608x3072 / 4608x3456",
    "image stabilizer": "Optical",
    "included accessories": "Charger",
    "light sensitivity iso": "Auto / 100 / 125 / 200 / 400 / 800 / 1600 / 3200",
    "lowest price": "Rs.11,395 Show all prices \u00bb",
    "max shutter speed": "1/2000",
    "memory type": "MultiMediaCard / SD / SDHC / SDXC",
    "metering modes": "Center-weighted / Multi / Spot",
    "microphone": "Yes",
    "min shutter speed": "15s (more than 51%)",
    "optical zoom": "5x (more than 61%)",
    "orientation sensor": "Yes",
    "product name": "Canon IXUS 125 HS",
    "product rating": "4 out of 5",
    "recording functions": "Blink Detection\n/ Face Detection\n/ Smile Detection",
    "red eye reduction": "Yes",
    "resolution": "16.1 MP (more than 84%)",
    "screen resolution": "461000 (more than 77%)",
    "screen size": "3\" (more than 62%)",
    "screen type": "LCD",
    "self timer delay": "2s / 10s",
    "sensor size": "1/2.3",
    "sensor type": "CMOS",
    "special effects": "Black & White / Color Accent / Color Swap / Contrast / Darker Skin Tone / Fisheye / Lighter Skin Tone / Monochrome / Neutral / Positive Film / Sepia / Soft Focus / Vivid",
    "user reviews": "Write a review",
    "video resolution": "320x240 / 640x424 / 1280x720 / 1920x1080",
    "viewfinder coverage": "100%",
    "weight": "135 g",
    "white balance": "Custom / Presets",
    "white balance presets": "Artificial\n/ Cloudy / Daylight / Sunny / Fluorescent / Outdoor / Tungsten / Underwater",
    "width": "93 mm"
}