{
    "3d": "Yes",
    "<page title>": "Sony DSC-HX9V digital camera prices, Shopping comparison for Sony DSC HX 9V, Buy online in India - ShopMania",
    "af illuminator": "Yes",
    "aperture": "F/3.3-5.9",
    "autofocus": "Contrast Detect\n/ Live View\n/ Multi-area\n/ Single",
    "battery": "Li-Ion",
    "body type": "Compact",
    "brand": "Sony",
    "category": "Digital Cameras",
    "connector type": "Composite / HDMI / USB",
    "continuous shooting speed": "10",
    "depth": "34 mm",
    "digital video format": "AVCHD / AVI / MPEG-4 / H.264",
    "digital zoom": "4x",
    "display form factor": "Fixed",
    "ean": "4905524768787, 4905524768800, 0876544747554, 0027242827240, 4905524768770, 0845251022704, 0876544747530, 0876544747509, 0845251022711, 0845251022728, 0876544747547",
    "exposure compensation": "-/+ 2 EV range, in 1/3 EV steps",
    "exposure modes": "Auto / Custom / Intelligent Auto / Manual / Program / Scene",
    "flash modes": "Auto / Off / On / Red Eye Reduction / Slow Speed Sync",
    "flash range": "4 m",
    "flash type": "Built-in",
    "focal length": "4.28 - 68.48 mm",
    "focal length equivalent to 35mm": "24 - 384 mm",
    "gps": "Yes",
    "height": "59 mm",
    "image format": "DCF / DPOF / JPEG / MPF / RAW",
    "image processor": "Bionz",
    "image ratio": "4:3 / 16:9",
    "image resolutions": "640x480 / 1920x1080 / 2048x1536 / 2592x1944 / 3072x2304 / 3264x2448 / 3456x2304 / 3456x2592 / 3648x2432 / 3648x2736 / 4000x2248 / 4000x3000 / 4320x2432 / 4320x3240 / 4608x2592 / 4608x3456",
    "image stabilizer": "Optical",
    "included accessories": "Carrying strap / Charger / USB cable",
    "installed memory": "19 MB",
    "light sensitivity iso": "Auto / 100 / 200 / 400 / 800 / 1600 / 3200",
    "live view": "Yes",
    "lowest price": "Rs.15,947 Show all prices \u00bb",
    "manual focus": "Yes",
    "max shutter speed": "1/1600",
    "memory type": "Memory Stick Duo / Memory Stick PRO Duo / Memory Stick PRO Duo High Speed / Memory Stick PRO-HG Duo / SD / SDHC / SDXC",
    "metering modes": "Center-weighted / Multi / Spot",
    "microphone": "Yes",
    "min shutter speed": "30s (more than 65%)",
    "number of focus points": "9",
    "optical zoom": "16x (more than 92%)",
    "orientation sensor": "Yes",
    "product name": "Sony DSC-HX9V",
    "product rating": "5 out of 5",
    "recording functions": "Blink Detection\n/ Face Detection\n/ HDR\n/ Panorama\n/ Smile Detection\n/ Sweep Panorama",
    "red eye reduction": "Yes",
    "resolution": "16.2 MP (more than 88%)",
    "screen resolution": "921000 (more than 84%)",
    "screen size": "3\" (more than 62%)",
    "screen type": "LCD",
    "self timer delay": "2s / 10s",
    "sensor size": "1/2.3",
    "sensor type": "BSI CMOS",
    "special effects": "Contrast / Saturation / Soft",
    "upc": "876544747554, 027242827240, 845251022704, 876544747530, 876544747509, 845251022711, 845251022728, 876544747547",
    "user reviews": "Read reviews\nWrite a review",
    "video resolution": "320x240 / 640x480 / 1280x720 / 1440x1080 / 1920x1080",
    "viewfinder type": "Optical",
    "weight": "245 g",
    "white balance": "Automatic / Custom / Presets",
    "white balance presets": "Cloudy / Daylight / Sunny / Fine / Flash / Fluorescent / Incandescent / Tungsten",
    "width": "105 mm"
}