{
    "<page title>": "Nikon D5300 Body Only Digital SLR Camera - Red",
    "aspect ratio": "3:2 (Horizontal; Vertical)",
    "battery": "Lithium-Ion EN-EL14a or EN-EL14 rechargeable battery & charger",
    "dimensions w x h x d": "125 x 98 x 76 mm (4.92 x 3.86 x 2.99\u2033)",
    "effective pixels": "24 megapixels",
    "focal length equiv": "1.5\u00d7",
    "gps": "BuiltIn",
    "hdmi": "Yes (Mini Type C)",
    "image stabilisation": "No",
    "iso sensitivity": "Auto, 100 - 12800 (25600 with boost)",
    "lcd screen size inch": "3.2\u2033",
    "max aperture": "N/A",
    "max resolution": "6000 x 4000",
    "max shutter speed": "1/4000 sec",
    "movie size": "N/A",
    "optical zoom": "No",
    "sensor size": "APS-C (23.5 x 15.6 mm)",
    "sensor type": "CMOS",
    "storage type": "SD/SDHC/SDXC",
    "total pixels": "24 megapixels",
    "usb": "USB 2.0 (480 Mbit/sec)",
    "weight inc batteries": "480 g (1.06 lb / 16.93 oz)",
    "wireless": "Optional"
}